cloudpulseclient/__init__.py
cloudpulseclient/exceptions.py
cloudpulseclient/i18n.py
cloudpulseclient/shell.py
cloudpulseclient/version.py
cloudpulseclient/common/__init__.py
cloudpulseclient/common/base.py
cloudpulseclient/common/httpclient.py
cloudpulseclient/common/utils.py
cloudpulseclient/openstack/__init__.py
cloudpulseclient/openstack/common/__init__.py
cloudpulseclient/openstack/common/_i18n.py
cloudpulseclient/openstack/common/cliutils.py
cloudpulseclient/openstack/common/apiclient/__init__.py
cloudpulseclient/openstack/common/apiclient/auth.py
cloudpulseclient/openstack/common/apiclient/base.py
cloudpulseclient/openstack/common/apiclient/client.py
cloudpulseclient/openstack/common/apiclient/exceptions.py
cloudpulseclient/openstack/common/apiclient/fake_client.py
cloudpulseclient/openstack/common/apiclient/utils.py
cloudpulseclient/tests/__init__.py
cloudpulseclient/tests/base.py
cloudpulseclient/tests/test_cloudpulseclient.py
cloudpulseclient/v1/__init__.py
cloudpulseclient/v1/client.py
cloudpulseclient/v1/cloudpulseservices.py
cloudpulseclient/v1/shell.py
python_cloudpulseclient-2015.3.3.dist-info/DESCRIPTION.rst
python_cloudpulseclient-2015.3.3.dist-info/METADATA
python_cloudpulseclient-2015.3.3.dist-info/RECORD
python_cloudpulseclient-2015.3.3.dist-info/WHEEL
python_cloudpulseclient-2015.3.3.dist-info/entry_points.txt
python_cloudpulseclient-2015.3.3.dist-info/metadata.json
python_cloudpulseclient-2015.3.3.dist-info/pbr.json
python_cloudpulseclient-2015.3.3.dist-info/top_level.txt
