Metadata-Version: 2.0
Name: python-cloudpulseclient
Version: 2015.3.3
Summary: A Python language binding for OpenStack CloudPulse.
Home-page: http://www.openstack.org/
Author: OpenStack
Author-email: openstack-dev@lists.openstack.org
License: UNKNOWN
Platform: UNKNOWN
Classifier: Environment :: OpenStack
Classifier: Intended Audience :: Information Technology
Classifier: Intended Audience :: System Administrators
Classifier: License :: OSI Approved :: Apache Software License
Classifier: Operating System :: POSIX :: Linux
Classifier: Programming Language :: Python
Classifier: Programming Language :: Python :: 2
Classifier: Programming Language :: Python :: 2.7
Classifier: Programming Language :: Python :: 3
Classifier: Programming Language :: Python :: 3.3
Classifier: Programming Language :: Python :: 3.4
Requires-Dist: Babel (>=1.3)
Requires-Dist: PyYAML (>=3.1.0)
Requires-Dist: iso8601 (>=0.1.9)
Requires-Dist: oslo.config (>=1.11.0)
Requires-Dist: oslo.i18n (>=1.5.0)
Requires-Dist: oslo.utils (>=1.4.0)
Requires-Dist: pbr (>=0.11,<2.0)
Requires-Dist: python-keystoneclient (>=1.3.0)
Requires-Dist: requests (>=2.5.2)
Requires-Dist: six (>=1.9.0)
Requires-Dist: stevedore (>=1.3.0)
